README.md
setup.py
nlhe_hu_engine/__init__.py
nlhe_hu_engine/constants.py
nlhe_hu_engine/engine.py
nlhe_hu_engine.egg-info/PKG-INFO
nlhe_hu_engine.egg-info/SOURCES.txt
nlhe_hu_engine.egg-info/dependency_links.txt
nlhe_hu_engine.egg-info/requires.txt
nlhe_hu_engine.egg-info/top_level.txt
test/test_engine.py